nxdk_pgraph_test_runner/__about__.py
nxdk_pgraph_test_runner/__init__.py
nxdk_pgraph_test_runner/__main__.py
nxdk_pgraph_test_runner/_ftp_server.py
nxdk_pgraph_test_runner/_nxdk_pgraph_tester_config.py
nxdk_pgraph_test_runner/_nxdk_pgraph_tester_progress_log.py
nxdk_pgraph_test_runner/_nxdk_pgraph_tester_test_output.py
nxdk_pgraph_test_runner/config.py
nxdk_pgraph_test_runner/emulator_output.py
nxdk_pgraph_test_runner/host_profile.py
nxdk_pgraph_test_runner/runner.py
nxdk_pgraph_test_runner-0.1.19.dist-info/METADATA
nxdk_pgraph_test_runner-0.1.19.dist-info/WHEEL
nxdk_pgraph_test_runner-0.1.19.dist-info/entry_points.txt
nxdk_pgraph_test_runner-0.1.19.dist-info/licenses/LICENSE.txt
nxdk_pgraph_test_runner-0.1.19.dist-info/RECORD
