Metadata-Version: 2.4
Name: nxdk-pgraph-test-runner
Version: 0.1.19
Summary: Executes and captures the results of https://github.com/abaire/nxdk_pgraph_tests in an emulator
Project-URL: Documentation, https://github.com/abaire/nxdk-pgraph-test-runner#readme
Project-URL: Issues, https://github.com/abaire/nxdk-pgraph-test-runner/issues
Project-URL: Source, https://github.com/abaire/nxdk-pgraph-test-runner
Author-email: Erik Abair <erik.abair@bearbrains.work>
License-Expression: MIT
License-File: LICENSE.txt
Keywords: nv2a,pgraph,xbox,xemu
Classifier: Development Status :: 3 - Alpha
Classifier: Programming Language :: Python
Classifier: Programming Language :: Python :: 3.10
Classifier: Programming Language :: Python :: 3.11
Classifier: Programming Language :: Python :: 3.12
Classifier: Programming Language :: Python :: Implementation :: CPython
Classifier: Programming Language :: Python :: Implementation :: PyPy
Requires-Python: >=3.10
Requires-Dist: glfw~=2.8.0
Requires-Dist: ifaddr~=0.2.0
Requires-Dist: mergedeep~=1.3.4
Requires-Dist: nxdk-pgraph-test-repacker~=0.0.4
Requires-Dist: platformdirs~=4.3.6
Requires-Dist: pyftpdlib~=2.0.1
Requires-Dist: pyopengl~=3.1.9
Requires-Dist: tomli-w~=1.2.0
Requires-Dist: tomli; python_version < '3.11'
